odoo/addons/shopinvader_assortment/README.rst
odoo/addons/shopinvader_assortment/__init__.py
odoo/addons/shopinvader_assortment/__manifest__.py
odoo/addons/shopinvader_assortment/demo/shopinvader_assortment_demo.xml
odoo/addons/shopinvader_assortment/i18n/shopinvader_assortment.pot
odoo/addons/shopinvader_assortment/models/__init__.py
odoo/addons/shopinvader_assortment/models/se_index.py
odoo/addons/shopinvader_assortment/models/shopinvader_backend.py
odoo/addons/shopinvader_assortment/readme/CONTRIBUTORS.rst
odoo/addons/shopinvader_assortment/readme/DESCRIPTION.rst
odoo/addons/shopinvader_assortment/readme/HISTORY.rst
odoo/addons/shopinvader_assortment/static/description/index.html
odoo/addons/shopinvader_assortment/tests/__init__.py
odoo/addons/shopinvader_assortment/tests/test_product_auto_bind.py
odoo/addons/shopinvader_assortment/views/shopinvader_backend.xml
odoo13_addon_shopinvader_assortment-13.0.2.0.0.dist-info/METADATA
odoo13_addon_shopinvader_assortment-13.0.2.0.0.dist-info/WHEEL
odoo13_addon_shopinvader_assortment-13.0.2.0.0.dist-info/top_level.txt
odoo13_addon_shopinvader_assortment-13.0.2.0.0.dist-info/RECORD
