Metadata-Version: 2.1
Name: odoo13-addon-shopinvader-assortment
Version: 13.0.2.0.0
Summary: Shopinvader Assortment
Home-page: https://github.com/shopinvader/odoo-shopinvader
Author: ACSONE SA/NV
License: AGPL-3
Platform: UNKNOWN
Classifier: Programming Language :: Python
Classifier: Framework :: Odoo
Classifier: License :: OSI Approved :: GNU Affero General Public License v3
Requires-Python: >=3.5
Requires-Dist: odoo13-addon-product-assortment
Requires-Dist: odoo13-addon-shopinvader
Requires-Dist: odoo13-addon-shopinvader-search-engine
Requires-Dist: odoo (<13.1dev,>=13.0a)
